resellerclub/__init__.py
resellerclub/exceptions.py
resellerclub/wrapper.py
resellerclub/client/__init__.py
resellerclub/client/base.py
resellerclub/client/customers.py
resellerclub/client/domains.py
resellerclub/client/urls/__init__.py
resellerclub/client/urls/base.py
resellerclub/client/urls/customers.py
resellerclub/client/urls/domains.py
resellerclub/client/urls/urls.py
resellerclub_python-0.0.1.dist-info/METADATA
resellerclub_python-0.0.1.dist-info/WHEEL
resellerclub_python-0.0.1.dist-info/licenses/LICENSE
resellerclub_python-0.0.1.dist-info/RECORD
